<?xml version = "1.0" standalone="yes"?>
<!-- This file has been generated by DOcplex version 2.9.133  -->
<CPLEXSolution version="1.0">
 <header
   problemName="CB-Planning_Route_Matching"
   objectiveValue="566.211"
  />
 <variables>
  <variable name="y_10_10_66_67_0" index="1616" value="1"/>
  <variable name="y_10_10_73_74_0" index="3234" value="1"/>
  <variable name="y_10_10_52_53_0" index="3812" value="1"/>
  <variable name="y_14_14_161_164_0" index="16245" value="1"/>
  <variable name="y_14_14_145_147_0" index="33139" value="1"/>
  <variable name="y_0_10_50_51_0" index="34394" value="1"/>
  <variable name="y_14_14_158_159_0" index="35127" value="1"/>
  <variable name="y_14_14_175_177_0" index="36819" value="1"/>
  <variable name="y_31_7_106_119_0" index="41485" value="1"/>
  <variable name="y_14_14_157_158_0" index="43835" value="1"/>
  <variable name="y_44_14_131_139_0" index="44506" value="1"/>
  <variable name="y_14_14_164_166_0" index="49589" value="1"/>
  <variable name="y_10_10_70_71_0" index="61958" value="1"/>
  <variable name="y_10_10_68_70_0" index="63978" value="1"/>
  <variable name="y_10_10_74_76_0" index="72878" value="1"/>
  <variable name="y_7_44_119_131_0" index="75671" value="1"/>
  <variable name="y_14_14_166_170_0" index="79894" value="1"/>
  <variable name="y_14_14_183_184_0" index="86962" value="1"/>
  <variable name="y_10_10_53_54_0" index="99068" value="1"/>
  <variable name="y_14_14_177_183_0" index="101993" value="1"/>
  <variable name="y_6_31_101_106_0" index="107441" value="1"/>
  <variable name="y_14_14_184_185_0" index="115627" value="1"/>
  <variable name="y_14_14_159_161_0" index="120177" value="1"/>
  <variable name="y_14_14_186_187_0" index="121954" value="1"/>
  <variable name="y_10_10_63_66_0" index="122280" value="1"/>
  <variable name="y_10_10_54_58_0" index="122731" value="1"/>
  <variable name="y_10_10_59_60_0" index="124979" value="1"/>
  <variable name="y_10_10_58_59_0" index="133672" value="1"/>
  <variable name="y_10_10_60_62_0" index="145000" value="1"/>
  <variable name="y_14_14_147_150_0" index="152171" value="1"/>
  <variable name="y_10_10_51_52_0" index="152550" value="1"/>
  <variable name="y_10_10_62_63_0" index="160021" value="1"/>
  <variable name="y_14_14_150_154_0" index="163366" value="1"/>
  <variable name="y_14_0_187_190_0" index="173390" value="1"/>
  <variable name="y_5_6_95_101_0" index="180717" value="1"/>
  <variable name="y_10_10_71_73_0" index="181130" value="1"/>
  <variable name="y_10_5_77_95_0" index="188633" value="1"/>
  <variable name="y_10_10_76_77_0" index="193287" value="1"/>
  <variable name="y_14_14_170_175_0" index="203469" value="1"/>
  <variable name="y_14_14_185_186_0" index="219432" value="1"/>
  <variable name="y_14_14_139_145_0" index="222971" value="1"/>
  <variable name="y_10_10_67_68_0" index="226461" value="1"/>
  <variable name="y_14_14_154_157_0" index="230533" value="1"/>
  <variable name="y_21_21_182_186_1" index="260900" value="1"/>
  <variable name="y_10_26_72_91_1" index="267975" value="1"/>
  <variable name="y_10_10_71_72_1" index="269790" value="1"/>
  <variable name="y_18_17_134_143_1" index="272990" value="1"/>
  <variable name="y_17_21_143_156_1" index="278372" value="1"/>
  <variable name="y_10_10_70_71_1" index="295563" value="1"/>
  <variable name="y_10_10_69_70_1" index="304244" value="1"/>
  <variable name="y_33_18_106_134_1" index="311881" value="1"/>
  <variable name="y_26_33_91_106_1" index="316516" value="1"/>
  <variable name="y_21_21_158_159_1" index="319623" value="1"/>
  <variable name="y_21_21_174_177_1" index="328195" value="1"/>
  <variable name="y_21_21_181_182_1" index="331930" value="1"/>
  <variable name="y_21_21_162_172_1" index="335497" value="1"/>
  <variable name="y_10_10_65_69_1" index="341082" value="1"/>
  <variable name="y_21_21_177_178_1" index="349774" value="1"/>
  <variable name="y_10_10_50_52_1" index="362390" value="1"/>
  <variable name="y_21_21_186_189_1" index="370928" value="1"/>
  <variable name="y_21_21_156_158_1" index="390980" value="1"/>
  <variable name="y_10_10_52_63_1" index="406183" value="1"/>
  <variable name="y_0_10_50_50_1" index="412943" value="1"/>
  <variable name="y_21_21_178_181_1" index="423613" value="1"/>
  <variable name="y_21_21_159_162_1" index="426802" value="1"/>
  <variable name="y_21_0_189_190_1" index="435101" value="1"/>
  <variable name="y_10_10_63_65_1" index="444588" value="1"/>
  <variable name="y_21_21_173_174_1" index="453908" value="1"/>
  <variable name="y_21_21_172_173_1" index="462589" value="1"/>
 </variables>
</CPLEXSolution>
